pdc_bot_updater/client/updater.py
pdc_bot_updater/core/meta.py
pdc_bot_updater/publisher/publish.py
pdc_bot_updater-1.2.6.dist-info/LICENSE
pdc_bot_updater-1.2.6.dist-info/WHEEL
pdc_bot_updater-1.2.6.dist-info/METADATA
pdc_bot_updater-1.2.6.dist-info/RECORD
