Metadata-Version: 2.1
Name: pdc-bot-updater
Version: 1.2.6
Summary: pdc shipment aplication bot
Author: kampretcode
Author-email: manorder123@gmail.com
Requires-Python: >=3.9,<4.0
Classifier: Programming Language :: Python :: 3
Classifier: Programming Language :: Python :: 3.10
Classifier: Programming Language :: Python :: 3.9
Requires-Dist: google-cloud-storage (>=2.2.1,<3.0.0)
Requires-Dist: pydantic (>=1.9.0,<2.0.0)
Requires-Dist: requests (>=2.27.1,<3.0.0)
Requires-Dist: tqdm (>=4.64.0,<5.0.0)
